odoo/addons/ssi_meeting_quality_control/README.rst
odoo/addons/ssi_meeting_quality_control/__init__.py
odoo/addons/ssi_meeting_quality_control/__manifest__.py
odoo/addons/ssi_meeting_quality_control/models/__init__.py
odoo/addons/ssi_meeting_quality_control/models/calendar_event.py
odoo/addons/ssi_meeting_quality_control/static/description/icon.png
odoo14_addon_ssi_meeting_quality_control-14.0.1.0.0.dist-info/METADATA
odoo14_addon_ssi_meeting_quality_control-14.0.1.0.0.dist-info/WHEEL
odoo14_addon_ssi_meeting_quality_control-14.0.1.0.0.dist-info/top_level.txt
odoo14_addon_ssi_meeting_quality_control-14.0.1.0.0.dist-info/RECORD
